AssayingAnomalies/Testing_File.py
AssayingAnomalies/__init__.py
AssayingAnomalies/config.py
AssayingAnomalies/setup_library.py
AssayingAnomalies/use_library.py
AssayingAnomalies/Functions/Gibbs.py
AssayingAnomalies/Functions/__init__.py
AssayingAnomalies/Functions/assignToPtf.py
AssayingAnomalies/Functions/assign_to_portfolios.py
AssayingAnomalies/Functions/calcPtfRets.py
AssayingAnomalies/Functions/calcTcosts.py
AssayingAnomalies/Functions/calculate_car3_for_permno.py
AssayingAnomalies/Functions/calculate_ivol_for_permno.py
AssayingAnomalies/Functions/check_and_clean_sort_variables.py
AssayingAnomalies/Functions/crspGibbsBuildv01.py
AssayingAnomalies/Functions/estFactorRegs.py
AssayingAnomalies/Functions/fill_missing_tcosts.py
AssayingAnomalies/Functions/fill_months.py
AssayingAnomalies/Functions/getCRSPData.py
AssayingAnomalies/Functions/getCompustatData.py
AssayingAnomalies/Functions/getFFDailyFactors.py
AssayingAnomalies/Functions/getFFFactors.py
AssayingAnomalies/Functions/getFredData.py
AssayingAnomalies/Functions/get_crsp_daily_data.py
AssayingAnomalies/Functions/grs_test_p.py
AssayingAnomalies/Functions/makeAbdiRanaldi.py
AssayingAnomalies/Functions/makeBetas.py
AssayingAnomalies/Functions/makeBivSortInd.py
AssayingAnomalies/Functions/makeCOMPUSTATDerivedVariables.py
AssayingAnomalies/Functions/makeCOMPUSTATVariables.py
AssayingAnomalies/Functions/makeCRSPDailyData.py
AssayingAnomalies/Functions/makeCRSPDailyDerivedVariables.py
AssayingAnomalies/Functions/makeCRSPDerivedVariables.py
AssayingAnomalies/Functions/makeCRSPMonthlyData.py
AssayingAnomalies/Functions/makeCorwinSchultz.py
AssayingAnomalies/Functions/makeFF10Indus.py
AssayingAnomalies/Functions/makeFF17Indus.py
AssayingAnomalies/Functions/makeFF49Indus.py
AssayingAnomalies/Functions/makeGibbs.py
AssayingAnomalies/Functions/makeIndustryClassifications.py
AssayingAnomalies/Functions/makeIndustryReturns.py
AssayingAnomalies/Functions/makeKyleObizhaeva.py
AssayingAnomalies-2.0.6.dist-info/LICENSE
AssayingAnomalies-2.0.6.dist-info/METADATA
AssayingAnomalies-2.0.6.dist-info/WHEEL
AssayingAnomalies-2.0.6.dist-info/top_level.txt
AssayingAnomalies-2.0.6.dist-info/RECORD
