Metadata-Version: 2.1
Name: AssayingAnomalies
Version: 2.0.6
Summary: This library is a Python implementation of the MATLAB Toolkit that accompanies Novy-Marx and Velikov (2023) and is to be used for empirical academic asset pricing research, particularly focused on studying anomalies in the cross-section of stock returns.
Author: Joshua Lawson
Author-email: jlaws13@simon.rochester.edu
License-File: LICENSE
Requires-Dist: bcrypt >=4.1.3
Requires-Dist: certifi >=2024.2.2
Requires-Dist: cffi >=1.16.0
Requires-Dist: charset-normalizer >=3.3.2
Requires-Dist: click >=8.1.7
Requires-Dist: cloudpickle >=3.0.0
Requires-Dist: colorama >=0.4.6
Requires-Dist: contourpy >=1.2.1
Requires-Dist: cryptography >=42.0.7
Requires-Dist: cycler >=0.12.1
Requires-Dist: dask >=2024.5.1
Requires-Dist: dask-expr >=1.1.1
Requires-Dist: docutils >=0.21.2
Requires-Dist: fonttools >=4.51.0
Requires-Dist: fsspec >=2024.5.0
Requires-Dist: greenlet >=3.0.3
Requires-Dist: idna >=3.7
Requires-Dist: importlib-metadata >=7.1.0
Requires-Dist: importlib-resources >=6.4.0
Requires-Dist: jaraco.classes >=3.4.0
Requires-Dist: jaraco.context >=5.3.0
Requires-Dist: jaraco.functools >=4.0.1
Requires-Dist: keyring >=25.2.1
Requires-Dist: kiwisolver >=1.4.5
Requires-Dist: locket >=1.0.0
Requires-Dist: markdown-it-py >=3.0.0
Requires-Dist: matplotlib >=3.9.0
Requires-Dist: mdurl >=0.1.2
Requires-Dist: more-itertools >=10.2.0
Requires-Dist: nh3 >=0.2.17
Requires-Dist: numpy >=2.0.0
Requires-Dist: packaging >=23.2
Requires-Dist: pandas >=2.2.2
Requires-Dist: paramiko >=3.4.0
Requires-Dist: partd >=1.4.2
Requires-Dist: patsy >=0.5.6
Requires-Dist: pexpect >=4.9.0
Requires-Dist: pillow >=10.3.0
Requires-Dist: pkginfo >=1.10.0
Requires-Dist: psycopg2-binary >=2.9.9
Requires-Dist: ptyprocess >=0.7.0
Requires-Dist: pyarrow >=16.1.0
Requires-Dist: pycparser >=2.22
Requires-Dist: Pygments >=2.18.0
Requires-Dist: PyNaCl >=1.5.0
Requires-Dist: pyparsing >=3.1.2
Requires-Dist: python-dateutil >=2.9.0.post0
Requires-Dist: pytz >=2024.1
Requires-Dist: pywin32-ctypes >=0.2.2
Requires-Dist: PyYAML >=6.0.1
Requires-Dist: readme-renderer >=43.0
Requires-Dist: requests >=2.32.2
Requires-Dist: requests-toolbelt >=1.0.0
Requires-Dist: rfc3986 >=2.0.0
Requires-Dist: rich >=13.7.1
Requires-Dist: scipy >=1.14.0
Requires-Dist: setuptools >=70.0.0
Requires-Dist: six >=1.16.0
Requires-Dist: SQLAlchemy >=2.0.30
Requires-Dist: statsmodels >=0.14.2
Requires-Dist: toolz >=0.12.1
Requires-Dist: twine >=5.1.0
Requires-Dist: typing-extensions >=4.11.0
Requires-Dist: tzdata >=2024.1
Requires-Dist: urllib3 >=2.2.1
Requires-Dist: wheel >=0.43.0
Requires-Dist: wrds >=3.2.0
Requires-Dist: zipp >=3.18.2
